model2smtlib/__init__.py
model2smtlib/_version.py
model2smtlib/translate.py
model2smtlib/bilayer/__init__.py
model2smtlib/bilayer/translate.py
model2smtlib/chime/__init__.py
model2smtlib/chime/translate.py
model2smtlib/gromet/__init__.py
model2smtlib/gromet/translate.py
model2smtlib-1.2.0.dist-info/LICENSE
model2smtlib-1.2.0.dist-info/METADATA
model2smtlib-1.2.0.dist-info/WHEEL
model2smtlib-1.2.0.dist-info/top_level.txt
model2smtlib-1.2.0.dist-info/RECORD
