Metadata-Version: 2.1
Name: model2smtlib
Version: 1.2.0
Summary: Model to SMT-Lib converter
Home-page: 
Author: Dan Bryce
Author-email: dbryce@sift.net
License: MIT
License-File: LICENSE
Requires-Dist: pysmt
